SQLAlchemy_Wrapper-1.9.1.dist-info/DESCRIPTION.rst
SQLAlchemy_Wrapper-1.9.1.dist-info/METADATA
SQLAlchemy_Wrapper-1.9.1.dist-info/RECORD
SQLAlchemy_Wrapper-1.9.1.dist-info/WHEEL
SQLAlchemy_Wrapper-1.9.1.dist-info/metadata.json
SQLAlchemy_Wrapper-1.9.1.dist-info/top_level.txt
sqlalchemy_wrapper/__init__.py
sqlalchemy_wrapper/_compat.py
sqlalchemy_wrapper/helpers.py
sqlalchemy_wrapper/main.py
sqlalchemy_wrapper/paginator.py
